aind_large_scale_cellpose/__init__.py
aind_large_scale_cellpose/segment.py
aind_large_scale_cellpose/cellpose_segmentation/__init__.py
aind_large_scale_cellpose/cellpose_segmentation/combine_gradients.py
aind_large_scale_cellpose/cellpose_segmentation/compute_flows.py
aind_large_scale_cellpose/cellpose_segmentation/compute_masks.py
aind_large_scale_cellpose/cellpose_segmentation/compute_percentiles.py
aind_large_scale_cellpose/cellpose_segmentation/predict_gradients.py
aind_large_scale_cellpose/cellpose_segmentation/_shared/__init__.py
aind_large_scale_cellpose/cellpose_segmentation/_shared/types.py
aind_large_scale_cellpose/cellpose_segmentation/utils/__init__.py
aind_large_scale_cellpose/cellpose_segmentation/utils/utils.py
aind_large_scale_cellpose-0.0.6.dist-info/LICENSE
aind_large_scale_cellpose-0.0.6.dist-info/METADATA
aind_large_scale_cellpose-0.0.6.dist-info/WHEEL
aind_large_scale_cellpose-0.0.6.dist-info/top_level.txt
aind_large_scale_cellpose-0.0.6.dist-info/RECORD
