Metadata-Version: 2.1
Name: aind_large_scale_cellpose
Version: 0.0.6
Summary: Large-scale prediction with cellpose
Author: Allen Institute for Neural Dynamics
License: MIT
Classifier: Programming Language :: Python :: 3
Requires-Python: >=3.9
License-File: LICENSE
Requires-Dist: aind-large-scale-prediction ==1.0.0
Requires-Dist: scikit-image ==0.22.0
Requires-Dist: matplotlib ==3.9.0
Requires-Dist: scipy ==1.11.3
Requires-Dist: cellpose ==3.0.5
Requires-Dist: numba ==0.59.1
Provides-Extra: dev
Requires-Dist: black ; extra == 'dev'
Requires-Dist: coverage ; extra == 'dev'
Requires-Dist: flake8 ; extra == 'dev'
Requires-Dist: interrogate ; extra == 'dev'
Requires-Dist: isort ; extra == 'dev'
Requires-Dist: Sphinx ; extra == 'dev'
Requires-Dist: furo ; extra == 'dev'
